AUTHORS.rst
CONTRIBUTING.rst
HISTORY.rst
LICENSE
MANIFEST.in
README.rst
setup.cfg
setup.py
django_username_tools.egg-info/PKG-INFO
django_username_tools.egg-info/SOURCES.txt
django_username_tools.egg-info/dependency_links.txt
django_username_tools.egg-info/not-zip-safe
django_username_tools.egg-info/requires.txt
django_username_tools.egg-info/top_level.txt
username_tools/__init__.py
username_tools/admin.py
username_tools/apps.py
username_tools/blacklist.py
username_tools/fields.py
username_tools/models.py
username_tools/settings.py
username_tools/utils.py
username_tools/views.py
username_tools/migrations/0001_initial.py
username_tools/migrations/__init__.py
username_tools/static/css/username_tools.css
username_tools/static/js/username_tools.js
username_tools/templates/username_tools/base.html