Metadata-Version: 1.1
Name: django-username-tools
Version: 0.1.3
Summary: Username validation fields and utilities for Django
Home-page: https://github.com/poudel/django-username-tools
Author: keshaB Paudel
Author-email: self@keshab.net
License: MIT
Keywords: django-username-tools
Platform: UNKNOWN
Classifier: Development Status :: 4 - Beta
Classifier: Framework :: Django
Classifier: Framework :: Django :: 2.0
Classifier: Intended Audience :: Developers
Classifier: License :: OSI Approved :: MIT License
Classifier: Natural Language :: English
Classifier: Programming Language :: Python :: 3.5
Classifier: Programming Language :: Python :: 3.6
